zatca_csr_generator/__init__.py
zatca_csr_generator/zatca_csr.py
zatca_csr_generator-3.1.1.dist-info/LICENSE
zatca_csr_generator-3.1.1.dist-info/METADATA
zatca_csr_generator-3.1.1.dist-info/WHEEL
zatca_csr_generator-3.1.1.dist-info/top_level.txt
zatca_csr_generator-3.1.1.dist-info/RECORD
