Metadata-Version: 2.1
Name: zatca_csr_generator
Version: 3.1.1
Summary: Zatca Csr Generator generates the certificate signing request for zatca phase2, It is takes informations and parameters from the user and returns the csr in base64 ready to submit to zatca
Home-page: https://github.com/bilaljmal/zatca_csr_generator
Author: Muhammad Bilal
Author-email: bilaljmal@gmail.com
Classifier: Development Status :: 5 - Production/Stable
Classifier: Intended Audience :: Developers
Classifier: License :: OSI Approved :: MIT License
Classifier: Programming Language :: Python :: 3
Classifier: Programming Language :: Python :: 3.6
Classifier: Programming Language :: Python :: 3.7
Classifier: Programming Language :: Python :: 3.8
Classifier: Programming Language :: Python :: 3.9
Classifier: Programming Language :: Python :: 3.10
Classifier: Programming Language :: Python :: 3.11
Classifier: Programming Language :: Python :: 3.12
License-File: LICENSE
Requires-Dist: cryptography
